raveforce/__init__.py
raveforce/core.py
raveforce-0.2.4.dist-info/LICENSE
raveforce-0.2.4.dist-info/METADATA
raveforce-0.2.4.dist-info/WHEEL
raveforce-0.2.4.dist-info/top_level.txt
raveforce-0.2.4.dist-info/RECORD
