Metadata-Version: 2.1
Name: raveforce
Version: 0.2.4
Summary: An OpenAI Gym style toolkit for music generation experiments.
Home-page: https://github.com/chaosprint/RaveForce
Author: Qichao Lan (chaosprint)
Author-email: chaosprint@gmail.com
License: MIT
Platform: UNKNOWN
Classifier: License :: OSI Approved :: MIT License
Classifier: Programming Language :: Python
Classifier: Programming Language :: Python :: 3
Classifier: Programming Language :: Python :: 3.6
Classifier: Programming Language :: Python :: Implementation :: CPython
Classifier: Programming Language :: Python :: Implementation :: PyPy
Requires-Python: >=3.6.0
License-File: LICENSE
Requires-Dist: wasmer
Requires-Dist: numpy
Requires-Dist: wasmer-compiler-cranelift
